pdf_pkg/__init__.py
pdf_pkg/pdf_generator.py
recipe_pdf_generator-0.1.0.dist-info/METADATA
recipe_pdf_generator-0.1.0.dist-info/WHEEL
recipe_pdf_generator-0.1.0.dist-info/top_level.txt
recipe_pdf_generator-0.1.0.dist-info/RECORD
