Metadata-Version: 2.1
Name: recipe-pdf-generator
Version: 0.1.0
Summary: A library for generating PDF versions of recipes
Requires-Dist: reportlab (==3.6.1)
